LICENSE
MANIFEST.in
README.rst
setup.cfg
setup.py
easysnmp/__init__.py
easysnmp/compat.py
easysnmp/easy.py
easysnmp/exceptions.py
easysnmp/helpers.py
easysnmp/interface.c
easysnmp/interface.cpython-38-x86_64-linux-gnu.so
easysnmp/session.py
easysnmp/simple_bitarray.h
easysnmp/utils.py
easysnmp/variables.py
easysnmp/__pycache__/__init__.cpython-38.pyc
easysnmp/__pycache__/compat.cpython-38.pyc
easysnmp/__pycache__/easy.cpython-38.pyc
easysnmp/__pycache__/exceptions.cpython-38.pyc
easysnmp/__pycache__/helpers.cpython-38.pyc
easysnmp/__pycache__/session.cpython-38.pyc
easysnmp/__pycache__/utils.cpython-38.pyc
easysnmp/__pycache__/variables.cpython-38.pyc
easysnmp2.egg-info/PKG-INFO
easysnmp2.egg-info/SOURCES.txt
easysnmp2.egg-info/dependency_links.txt
easysnmp2.egg-info/top_level.txt