Metadata-Version: 1.1
Name: easysnmp2
Version: 0.3.1
Summary: A blazingly fast and Pythonic SNMP library based on the official Net-SNMP bindings - Fork of unmaintained easysnmp
Home-page: https://github.com/MichalMazurek/easysnmp2
Author: Michal Mazurek
Author-email: mazurek.michal@gmail.com
License: BSD
Platform: UNKNOWN
Classifier: Development Status :: 4 - Beta
Classifier: Intended Audience :: Developers
Classifier: License :: OSI Approved :: BSD License
Classifier: Operating System :: OS Independent
Classifier: Programming Language :: Python
Classifier: Programming Language :: Python :: 3.3
Classifier: Programming Language :: Python :: 3.4
Classifier: Programming Language :: Python :: 3.5
Classifier: Programming Language :: Python :: 3.6
Classifier: Programming Language :: Python :: 3.7
Classifier: Programming Language :: Python :: 3.8
Classifier: Topic :: System :: Networking
Classifier: Topic :: System :: Networking :: Monitoring
